{"origem": "apoia.se", "categoria_teste_mencoes": {"saloes_humor": false, "hqmix": false, "ccxp": false, "fiq": false, "angelo_agostini": false, "politica": false, "questoes_genero": false, "lgbtqiamais": false, "terror": false, "humor": false, "herois": false, "disputa": false, "ficcao_cientifica": false, "fantasia": false, "folclore": false, "zine": false, "webformatos": false, "erotismo": false, "religiosidade": false, "jogos": false, "midia_independente": false}, "recompensas_menor_nominal": 5.0, "recompensas_menor_ajustado": 7.280084180798532, "recompensas_quantidade": 5, "autoria_id": "9d89c889-623e-4f72-adec-6da73886034b", "autoria_nome": "shiki animes", "autoria_nome_publico": "shiki animes", "autoria_classificacao": "outros", "autoria_classificacao_id": 5, "social_seguidores": 0, "social_newsletter": false, "social_sub_contribuicoes_amigos": 0, "social_sub_novos_seguidores": 0, "social_sub_posts_projeto": 0, "social_projetos_contribuidos": 0, "social_projetos_publicados": 0, "geral_municipio": "Santo Andr\u00e9", "geral_uf": "SP", "geral_uf_br": "SP", "geral_city_id": 5246, "geral_content_rating": null, "geral_contributed_by_friends": null, "geral_capa_imagem": false, "geral_capa_video": false, "geral_dias_campanha": 2841, "geral_data_fim": "", "geral_data_ini": "2017-07-21T02:50:25.689", "geral_meta": 100, "geral_meta_corrigida": 145.60168361597061, "geral_arrecadado": 0, "geral_arrecadado_corrigido": 0.0, "geral_percentual_arrecadado": 0.0, "geral_conteudo_adulto": false, "geral_posts": 0, "geral_project_id": "59716bf1d0bc3e03000c8301", "geral_modalidade": "sub", "geral_titulo": "Shiki Animes", "geral_status": "published", "geral_total_contribuicoes": 0, "geral_total_apoiadores": 0, "geral_sobre": "O objetivo da campanha \u00e9 adquirir patrocino para melhorar a quantidade e qualidade das postagem do blog. Criar um cronograma com as postagens, novas tags e assim trazer mais p\u00fablico para acessar o blog. :)"}