{"origem": "catarse", "mencoes_saloes_humor": false, "mencoes_hqmix": false, "mencoes_ccxp": false, "mencoes_fiq": false, "mencoes_angelo_agostini": false, "mencoes_politica": true, "mencoes_questoes_genero": false, "mencoes_lgbtqiamais": false, "mencoes_terror": true, "mencoes_humor": false, "mencoes_herois": false, "mencoes_disputa": false, "mencoes_ficcao_cientifica": false, "mencoes_fantasia": false, "mencoes_folclore": false, "mencoes_zine": false, "mencoes_webformatos": false, "mencoes_erotismo": true, "mencoes_religiosidade": false, "mencoes_jogos": true, "mencoes_midia_independente": false, "recompensas_menor_nominal": 170.0, "recompensas_menor_ajustado": 246.8328857401763, "recompensas_quantidade": 1, "autoria_id": 786864, "autoria_nome": "diana assun\u00e7\u00e3o zambrotti doria", "autoria_nome_publico": "crow", "autoria_classificacao": "feminino", "social_seguidores": 19, "social_newsletter": true, "social_sub_contribuicoes_amigos": true, "social_sub_novos_seguidores": true, "social_sub_posts_projeto": true, "social_projetos_contribuidos": 5, "social_projetos_publicados": 1, "geral_municipio": "Bras\u00edlia", "geral_uf": "DF", "geral_uf_br": "DF", "geral_city_id": 886, "geral_content_rating": 1, "geral_contributed_by_friends": false, "geral_capa_imagem": false, "geral_capa_video": true, "geral_dias_campanha": 40, "geral_data_fim": "2017-11-29T01:59:59.999999", "geral_data_ini": "2017-10-19T18:21:35.633789", "geral_meta": 12000.0, "geral_meta_corrigida": 17423.49781695362, "geral_arrecadado": 4390.0, "geral_arrecadado_corrigido": 6374.096284702199, "geral_percentual_arrecadado": 36.583333333333336, "geral_conteudo_adulto": false, "geral_posts": 1, "geral_project_id": 65380, "geral_modalidade": "aon", "geral_titulo": "Sobre os Corvos Mortos", "geral_status": "failed", "geral_total_contribuicoes": 61, "geral_total_apoiadores": 61, "topico_0": 0.2, "topico_1": 0.2, "topico_2": 0.2, "topico_3": 0.0, "topico_4": 0.0, "topico_5": 0.0, "topico_6": 0.2, "topico_7": 0.2, "topico_8": 0.0, "topico_9": 0.2, "topico_10": 0.2, "topico_11": 0.4, "topico_12": 0.4, "topico_13": 0.0, "topico_14": 0.0, "topico_15": 0.4, "topico_16": 0.2, "topico_17": 0.2, "topico_18": 0.2, "topico_19": 0.4, "topico_20": 0.2, "topico_21": 0.0, "topico_22": 0.4, "topico_23": 0.4, "topico_24": 0.2, "topico_25": 0.8, "topico_26": 0.4, "topico_27": 0.0, "topico_28": 0.0, "topico_29": 0.2, "topico_30": 0.4, "topico_31": 0.0, "topico_32": 0.4, "topico_33": 0.2, "topico_34": 0.6, "topico_35": 0.0, "topico_36": 0.0, "topico_37": 0.0, "topico_38": 0.0, "topico_39": 0.0, "topico_40": 0.2, "topico_41": 0.2, "topico_42": 0.2, "topico_43": 0.0, "topico_44": 0.2, "topico_45": 0.4, "topico_46": 0.4, "topico_47": 0.2, "topico_48": 0.0, "topico_49": 0.6, "geral_sobre": "SCM \u00e9 uma hist\u00f3ria sobre... er... sobre corvos mortos. Mas o que s\u00e3o eles? Por que morreram? E o que isso tem a ver com os 3 jovens que dividem uma casa num bairro simples de Vancouver? As respostas est\u00e3o espalhadas pelas mem\u00f3rias de Maurice, um homem que fala pouco mas escreve tudo em seus di\u00e1rios. O que come\u00e7ou nos anos 90 como uma terapia para que ele conseguisse superar seus traumas e medos hoje \u00e9 um registro de segredos de valor inestim\u00e1vel. Com essas p\u00e1ginas em m\u00e3os, Eric - velho amigo de Maurice - vai descobrir um mundo de paranoia, sangue e horror onde nada \u00e9 o que parece. SCM \u00e9 uma carta de amor ao mist\u00e9rio e ao horror. Inspirada em crimes reais das \u00faltimas d\u00e9cadas, ela abusa de imagens desconcertantes e met\u00e1foras que se confundem com a realidade. Vale ressaltar que ele aborda temas como o uso de drogas, suic\u00eddio e sexualidade, e NENHUM deles sob perspectiva m\u00e9dica ou pol\u00edtica. Voc\u00ea pode ler aqui as primeiras 15 p\u00e1ginas da vers\u00e3o web. A vers\u00e3o impressa ser\u00e1 reformada para ficar mais bonita e completa <3 Esse \u00e9 o primeiro volume de uma s\u00e9rie que pode se estender at\u00e9 3 volumes. Recomendado para maiores de 18 anos. Maurice nem fez 30 anos, mas j\u00e1 perdeu o pai num acidente e est\u00e1 prestes a perder a m\u00e3e para o c\u00e2ncer. Seu \u00fanico objetivo \u00e9 mant\u00ea-la viva, e para pagar os custos m\u00e9dicos ele aluga quartos vazios da casa que herdou. \u00c9 um objetivo com prazo de validade bem curto, e o que sobra pra fazer quando acabar...? Lavi tem 21 anos e \u00e9 inquilina do Maurice. \u00c9 uma das duas \u00fanicas alunas do curso de computa\u00e7\u00e3o na universidade, e sonha com uma carreira brilhante na Microsoft. Infelizmente, seu futuro \u00e9 amea\u00e7ado por um stalker - ou \u00e9 isso que ela pensa, antes de descobrir que o buraco \u00e9 muito mais em baixo. Eric tem 19 anos e ningu\u00e9m sabe ao certo o que ele faz, ou de onde tira dinheiro pra alugar um quarto na casa do Maurice. O fato \u00e9 que ele paga, e o Maurice n\u00e3o se importa o suficiente pra perguntar como. Est\u00e1 sempre com uma cerveja na m\u00e3o, cigarros no bolso e alguma marca de briga no rosto. Crow (aka Diana Doria) tem 23 anos e trabalha com concept art para jogos, ao mesmo tempo que estuda design na UnB e brinca de escrever quadrinhos. Sobre os Corvos Mortos \u00e9 sua primeira hist\u00f3ria autoral impressa."}