{"_id": "5caebc4038fa9246194b2f97", "about": {"what": "MANG\u00c1 INDEPEDENTE", "photo": "https://s3.amazonaws.com/assets.apoia.se/campaigns/5caebb17c1da4e92176a1167%7C5caebc4038fa9246194b2f97/user-campaign-about-photo%7CIMG_20191119_205957_606-20191206_18045913.jpg", "slogan": "Uma aventura do Brasil para o Mundo", "desc": "<p style=\"font-size: 16px;\">Ol\u00e1 GUARDI\u00d5ES!!!</p><p style=\"font-size: 16px;\">Sejam muito bem vindos, sou Roberto Dav\u00ed o Autor dessa humilde Hist\u00f3ria que surgiu do meu sonho de fazer mang\u00e1.</p><p style=\"font-size: 16px;\">Criei essa campanha com o objetivo de conseguir apoiadores que tenham interesse de continuar acompanhando Guardi\u00f5es, para que eu possa manter o Mang\u00e1 em Publica\u00e7\u00e3o.</p><p style=\"font-size: 16px;\">Se voc\u00ea levar em conta que eu desenho sozinho, n\u00e3o sai caro pra fazer um cap\u00edtulo, mas demora pra caramba, e como eu n\u00e3o nasci rico, tenho que trabalhar com outras coisas para pagar minhas contas e acabo ficando sem tempo para me dededicar ao MANG\u00c1.</p><p style=\"font-size: 16px;\">Esse \u00e9 o principal prop\u00f3sito dessa campanha!</p>", "cover": "https://s3.amazonaws.com/assets.apoia.se/campaigns/5caebb17c1da4e92176a1167%7C5caebc4038fa9246194b2f97/user-campaign-about-cover%7C1575662520683-20191206_18050578.png"}, "categories": ["Quadrinhos", "Desenho e Pintura"], "createdDate": "2019-04-11T04:02:08.452Z", "fundingModel": "monthly", "fundingFrequency": "recurring", "goals": [{"value": 700, "desc": "<p>Se Voc\u00ea acompanha o meu trabalho e tem interesse na continuidade do Mang\u00e1. Voc\u00ea pode ajudar com dois reais ou mais para que eu possa continuar nessa jornada.</p>", "title": "A minha meta \u00e9 poder continuar...", "_id": "5caf46ef3e91ef66191200a1"}], "name": "GUARDI\u00d5ES", "users": [{"_id": "5caebb17c1da4e92176a1167", "access": "owner"}], "status": "published", "social": [{"type": "instagram", "url": "https://www.instagram.com/guardioes_brasil", "_id": "5caf3df9c1da4e92176a12cf"}, {"type": "facebook", "url": "https://www.facebook.com/pg/Guardi%C3%B5es-Oficial-2668157856588521/posts/", "_id": "5caf3df9c1da4e92176a12ce"}, {"type": "facebook", "url": "https://www.facebook.com/roberto.davi.739", "_id": "5caf3df9c1da4e92176a12cd"}, {"type": "link", "url": "", "_id": "5deab472d5158d19c3abacb3"}], "supports": {"total": {"value": 0, "count": 0}, "count": 0}, "slug": "guardioes", "settings": {"admin": false}}